setup.cfg
setup.py
pyconsul/__init__.py
pyconsul.egg-info/PKG-INFO
pyconsul.egg-info/SOURCES.txt
pyconsul.egg-info/dependency_links.txt
pyconsul.egg-info/requires.txt
pyconsul.egg-info/top_level.txt