Metadata-Version: 1.1
Name: pyconsul
Version: 0.0.1
Summary: Python client for Consul (http://www.consul.io)
Home-page: https://github.com/hackliff/pyconsul
Author: Xavier Bruhiere
Author-email: xavier.bruhiere@gmail.com
License: MIT
Platform: UNKNOWN
Classifier: Development Status :: 2 - Pre-Alpha
Classifier: License :: OSI Approved :: MIT License
Classifier: Natural Language :: English
Classifier: Programming Language :: Python
Classifier: Programming Language :: Python :: 2.7
Classifier: Operating System :: OS Independent
Classifier: Topic :: Documentation
